bajson
