Metadata-Version: 2.1
Name: bajson
Version: 0.0.6
Summary: library for converting to/from json
Home-page: https://github.com/bakyazi/bajson
Author: bakyazi
Author-email: berkay.akyazi@gmail.com
License: MIT License
Platform: UNKNOWN
Classifier: Programming Language :: Python :: 3
Classifier: Development Status :: 1 - Planning
Classifier: Operating System :: OS Independent
Requires-Python: >=3.6
